atsphinx/mini18n/__init__.py
atsphinx/mini18n/py.typed
atsphinx/mini18n/templates/mini18n/index.html
atsphinx/mini18n/templates/mini18n/snippets/select-lang.html
atsphinx_mini18n-0.5.1.dist-info/METADATA
atsphinx_mini18n-0.5.1.dist-info/WHEEL
atsphinx_mini18n-0.5.1.dist-info/licenses/LICENSE
atsphinx_mini18n-0.5.1.dist-info/RECORD
