Metadata-Version: 2.4
Name: atsphinx-mini18n
Version: 0.5.1
Summary: Sphinx builder for i18n site on single deployment
Project-URL: Repository, https://github.com/atsphinx/mini18n
Project-URL: Issues, https://github.com/atsphinx/mini18n/issues
Project-URL: Document, https://atsphinx.github.io/mini18n/
Author-email: Kazuya Takei <myself@attakei.net>
License-Expression: Apache-2.0
License-File: LICENSE
Classifier: Development Status :: 4 - Beta
Classifier: Framework :: Sphinx
Classifier: Framework :: Sphinx :: Extension
Classifier: Intended Audience :: Developers
Classifier: License :: OSI Approved :: Apache Software License
Classifier: Operating System :: OS Independent
Classifier: Programming Language :: Python
Classifier: Programming Language :: Python :: 3 :: Only
Classifier: Programming Language :: Python :: 3.10
Classifier: Programming Language :: Python :: 3.11
Classifier: Programming Language :: Python :: 3.12
Classifier: Programming Language :: Python :: 3.13
Classifier: Topic :: Documentation :: Sphinx
Classifier: Topic :: Software Development
Classifier: Topic :: Software Development :: Documentation
Requires-Python: >=3.10
Requires-Dist: sphinx>=8.0.0
